openapi_spec_validator/__init__.py
openapi_spec_validator/__main__.py
openapi_spec_validator/exceptions.py
openapi_spec_validator/py.typed
openapi_spec_validator/readers.py
openapi_spec_validator/resources/schemas/v2.0/schema.json
openapi_spec_validator/resources/schemas/v3.0/schema.json
openapi_spec_validator/resources/schemas/v3.0.0/schema.json
openapi_spec_validator/resources/schemas/v3.1/schema.json
openapi_spec_validator/schemas/__init__.py
openapi_spec_validator/schemas/utils.py
openapi_spec_validator/shortcuts.py
openapi_spec_validator/validation/__init__.py
openapi_spec_validator/validation/caches.py
openapi_spec_validator/validation/decorators.py
openapi_spec_validator/validation/exceptions.py
openapi_spec_validator/validation/finders.py
openapi_spec_validator/validation/keywords.py
openapi_spec_validator/validation/protocols.py
openapi_spec_validator/validation/proxies.py
openapi_spec_validator/validation/registries.py
openapi_spec_validator/validation/types.py
openapi_spec_validator/validation/validators.py
openapi_spec_validator-0.7.0.dist-info/LICENSE
openapi_spec_validator-0.7.0.dist-info/METADATA
openapi_spec_validator-0.7.0.dist-info/WHEEL
openapi_spec_validator-0.7.0.dist-info/entry_points.txt
openapi_spec_validator-0.7.0.dist-info/RECORD
