Metadata-Version: 2.1
Name: openapi-spec-validator
Version: 0.7.0
Summary: OpenAPI 2.0 (aka Swagger) and OpenAPI 3 spec validator
Home-page: https://github.com/python-openapi/openapi-spec-validator
License: Apache-2.0
Keywords: openapi,swagger,schema
Author: Artur Maciag
Author-email: maciag.artur@gmail.com
Requires-Python: >=3.8.0,<4.0.0
Classifier: Development Status :: 4 - Beta
Classifier: Intended Audience :: Developers
Classifier: License :: OSI Approved :: Apache Software License
Classifier: Operating System :: OS Independent
Classifier: Programming Language :: Python :: 3
Classifier: Programming Language :: Python :: 3.8
Classifier: Programming Language :: Python :: 3.9
Classifier: Programming Language :: Python :: 3.10
Classifier: Programming Language :: Python :: 3.11
Classifier: Programming Language :: Python :: 3.12
Classifier: Topic :: Software Development :: Libraries
Classifier: Topic :: Software Development :: Libraries :: Python Modules
Provides-Extra: docs
Requires-Dist: importlib-resources (>=5.8,<7.0) ; python_version < "3.9"
Requires-Dist: jsonschema (>=4.18.0,<5.0.0)
Requires-Dist: jsonschema-spec (>=0.2.3,<0.3.0)
Requires-Dist: lazy-object-proxy (>=1.7.1,<2.0.0)
Requires-Dist: openapi-schema-validator (>=0.6.0,<0.7.0)
Project-URL: Repository, https://github.com/python-openapi/openapi-spec-validator
